technicals-0.1.0.dist-info/METADATA
technicals-0.1.0.dist-info/WHEEL
technicals-0.1.0.dist-info/entry_points.txt
technicals/_core.pyi
technicals/__init__.py
technicals/_core.abi3.so
technicals-0.1.0.dist-info/RECORD
