Metadata-Version: 2.4
Name: technicals
Version: 0.1.0
Summary: A library for constructing technical signals
Author-email: Zhenya Kovalyov <10375041+zhenyakovalyov@users.noreply.github.com>
Requires-Python: >=3.13
